padthai/__init__.py
padthai/dataset/__init__.py
padthai/dataset/dataset.py
padthai/flax/__init__.py
padthai/flax/model.py
padthai/gpt_neo/__init__.py
padthai/gpt_neo/model.py
padthai/mgpt/__init__.py
padthai/mgpt/model.py
padthai-0.3.0.dist-info/LICENSE
padthai-0.3.0.dist-info/METADATA
padthai-0.3.0.dist-info/WHEEL
padthai-0.3.0.dist-info/top_level.txt
padthai-0.3.0.dist-info/RECORD
