Metadata-Version: 2.1
Name: padthai
Version: 0.3.0
Summary: Make Pad Thai From few-shot learning 😉
Home-page: https://github.com/PyThaiNLP/padthai
Author: Wannaphong Phatthiyaphaibun
Author-email: wannaphong@yahoo.com
License: Apache Software License 2.0
Project-URL: Documentation, https://pythainlp.github.io/padthai/
Project-URL: Tutorials, https://github.com/PyThaiNLP/padthai/tree/main/notebooks
Project-URL: Source Code, https://github.com/PyThaiNLP/padthai
Project-URL: Bug Tracker, https://github.com/PyThaiNLP/padthai/issues
Platform: UNKNOWN
Requires-Python: >=3.6
Requires-Dist: transformers (<5.0)
